extensions_built_in/__init__.py
extensions_built_in/advanced_generator/Img2ImgGenerator.py
extensions_built_in/advanced_generator/PureLoraGenerator.py
extensions_built_in/advanced_generator/ReferenceGenerator.py
extensions_built_in/advanced_generator/__init__.py
extensions_built_in/concept_replacer/ConceptReplacer.py
extensions_built_in/concept_replacer/__init__.py
extensions_built_in/dataset_tools/DatasetTools.py
extensions_built_in/dataset_tools/SuperTagger.py
extensions_built_in/dataset_tools/SyncFromCollection.py
extensions_built_in/dataset_tools/__init__.py
extensions_built_in/image_reference_slider_trainer/ImageReferenceSliderTrainerProcess.py
extensions_built_in/image_reference_slider_trainer/__init__.py
extensions_built_in/sd_trainer/SDTrainer.py
extensions_built_in/sd_trainer/__init__.py
extensions_built_in/ultimate_slider_trainer/UltimateSliderTrainerProcess.py
extensions_built_in/ultimate_slider_trainer/__init__.py
jobs/BaseJob.py
jobs/ExtensionJob.py
jobs/ExtractJob.py
jobs/GenerateJob.py
jobs/MergeJob.py
jobs/ModJob.py
jobs/TrainJob.py
jobs/__init__.py
jobs/process/BaseExtensionProcess.py
jobs/process/BaseExtractProcess.py
jobs/process/BaseMergeProcess.py
jobs/process/BaseProcess.py
jobs/process/BaseSDTrainProcess.py
jobs/process/BaseTrainProcess.py
jobs/process/ExtractLoconProcess.py
jobs/process/ExtractLoraProcess.py
jobs/process/GenerateProcess.py
jobs/process/MergeLoconProcess.py
jobs/process/ModRescaleLoraProcess.py
jobs/process/TrainESRGANProcess.py
jobs/process/TrainFineTuneProcess.py
jobs/process/TrainSDRescaleProcess.py
jobs/process/TrainSliderProcess.py
jobs/process/TrainSliderProcessOld.py
jobs/process/TrainVAEProcess.py
jobs/process/__init__.py
jobs/process/models/__init__.py
jobs/process/models/vgg19_critic.py
notebooks/FLUX_1_dev_LoRA_Training.ipynb
notebooks/FLUX_1_schnell_LoRA_Training.ipynb
notebooks/SliderTraining.ipynb
notebooks/__init__.py
ostris_ai_toolkit/__init__.py
scripts/__init__.py
scripts/convert_cog.py
lora_train-0.1.2.dist-info/LICENSE
lora_train-0.1.2.dist-info/METADATA
lora_train-0.1.2.dist-info/WHEEL
lora_train-0.1.2.dist-info/top_level.txt
lora_train-0.1.2.dist-info/RECORD
