Metadata-Version: 2.1
Name: lora-train
Version: 0.1.2
Summary: A toolkit for AI-related tasks
Home-page: https://github.com/cozy-creator/ai-toolkit
Author: Cozy Creator
Author-email: teggyg123@gmail.com
Classifier: Programming Language :: Python :: 3
Classifier: License :: OSI Approved :: MIT License
Classifier: Operating System :: OS Independent
Requires-Python: >=3.6
License-File: LICENSE
Requires-Dist: torch
Requires-Dist: torchvision
Requires-Dist: safetensors
Requires-Dist: diffusers
Requires-Dist: transformers
Requires-Dist: lycoris-lora==1.8.3
Requires-Dist: flatten-json
Requires-Dist: pyyaml
Requires-Dist: oyaml
Requires-Dist: tensorboard
Requires-Dist: kornia
Requires-Dist: invisible-watermark
Requires-Dist: einops
Requires-Dist: accelerate
Requires-Dist: toml
Requires-Dist: albumentations
Requires-Dist: pydantic
Requires-Dist: omegaconf
Requires-Dist: k-diffusion
Requires-Dist: open-clip-torch
Requires-Dist: timm
Requires-Dist: prodigyopt
Requires-Dist: controlnet-aux==0.0.7
Requires-Dist: python-dotenv
Requires-Dist: bitsandbytes
Requires-Dist: hf-transfer
Requires-Dist: lpips
Requires-Dist: pytorch-fid
Requires-Dist: optimum-quanto
Requires-Dist: sentencepiece
Requires-Dist: huggingface-hub
Requires-Dist: peft
Requires-Dist: gradio
Requires-Dist: python-slugify
